square_legacy/__init__.py
square_legacy/api/__init__.py
square_legacy/api/apple_pay_api.py
square_legacy/api/bank_accounts_api.py
square_legacy/api/base_api.py
square_legacy/api/booking_custom_attributes_api.py
square_legacy/api/bookings_api.py
square_legacy/api/cards_api.py
square_legacy/api/cash_drawers_api.py
square_legacy/api/catalog_api.py
square_legacy/api/checkout_api.py
square_legacy/api/customer_custom_attributes_api.py
square_legacy/api/customer_groups_api.py
square_legacy/api/customer_segments_api.py
square_legacy/api/customers_api.py
square_legacy/api/devices_api.py
square_legacy/api/disputes_api.py
square_legacy/api/employees_api.py
square_legacy/api/events_api.py
square_legacy/api/gift_card_activities_api.py
square_legacy/api/gift_cards_api.py
square_legacy/api/inventory_api.py
square_legacy/api/invoices_api.py
square_legacy/api/labor_api.py
square_legacy/api/location_custom_attributes_api.py
square_legacy/api/locations_api.py
square_legacy/api/loyalty_api.py
square_legacy/api/merchant_custom_attributes_api.py
square_legacy/api/merchants_api.py
square_legacy/api/mobile_authorization_api.py
square_legacy/api/o_auth_api.py
square_legacy/api/order_custom_attributes_api.py
square_legacy/api/orders_api.py
square_legacy/api/payments_api.py
square_legacy/api/payouts_api.py
square_legacy/api/refunds_api.py
square_legacy/api/sites_api.py
square_legacy/api/snippets_api.py
square_legacy/api/subscriptions_api.py
square_legacy/api/team_api.py
square_legacy/api/terminal_api.py
square_legacy/api/transactions_api.py
square_legacy/api/v1_transactions_api.py
square_legacy/api/vendors_api.py
square_legacy/api/webhook_subscriptions_api.py
square_legacy/api_helper.py
square_legacy/client.py
square_legacy/configuration.py
square_legacy/exceptions/__init__.py
square_legacy/exceptions/api_exception.py
square_legacy/http/__init__.py
square_legacy/http/api_response.py
square_legacy/http/auth/__init__.py
square_legacy/http/auth/o_auth_2.py
square_legacy/http/http_call_back.py
squareup_legacy-41.0.0.20250319.dist-info/METADATA
squareup_legacy-41.0.0.20250319.dist-info/WHEEL
squareup_legacy-41.0.0.20250319.dist-info/RECORD
