Metadata-Version: 2.1
Name: squareup-legacy
Version: 41.0.0.20250319
Summary: Use Square APIs to manage and run business including payment, customer, product, inventory, and employee management.
Requires-Python: >=3.7,<4.0
Classifier: Programming Language :: Python :: 3
Classifier: Programming Language :: Python :: 3.7
Classifier: Programming Language :: Python :: 3.8
Classifier: Programming Language :: Python :: 3.9
Classifier: Programming Language :: Python :: 3.10
Classifier: Programming Language :: Python :: 3.11
Requires-Dist: apimatic-core (>=0.2.17,<0.3.0)
Requires-Dist: apimatic-core-interfaces (>=0.1.5,<0.2.0)
Requires-Dist: apimatic-requests-client-adapter (>=0.1.6,<0.2.0)
Requires-Dist: deprecation (>=2.1,<3.0)
